{"v":"5.6.2","fr":29.9700012207031,"ip":0,"op":59.0000024031193,"w":500,"h":500,"nm":"Target_2","ddd":0,"assets":[],"layers":[{"ddd":0,"ind":1,"ty":4,"nm":"Group 5","sr":1,"ks":{"o":{"a":1,"k":[{"i":{"x":[0.833],"y":[0.833]},"o":{"x":[0.167],"y":[0.167]},"t":0,"s":[0]},{"i":{"x":[0.833],"y":[0.833]},"o":{"x":[0.167],"y":[0.167]},"t":2.398,"s":[70]},{"i":{"x":[0.833],"y":[0.833]},"o":{"x":[0.167],"y":[0.167]},"t":3.596,"s":[0]},{"i":{"x":[0.833],"y":[0.833]},"o":{"x":[0.167],"y":[0.167]},"t":5.994,"s":[18]},{"i":{"x":[0.833],"y":[0.833]},"o":{"x":[0.167],"y":[0.167]},"t":7.193,"s":[0]},{"i":{"x":[0.833],"y":[0.833]},"o":{"x":[0.167],"y":[0.167]},"t":8.391,"s":[10]},{"i":{"x":[0.833],"y":[0.833]},"o":{"x":[0.167],"y":[0.167]},"t":9.59,"s":[51]},{"i":{"x":[0.833],"y":[0.833]},"o":{"x":[0.167],"y":[0.167]},"t":10.789,"s":[0]},{"i":{"x":[0.833],"y":[0.833]},"o":{"x":[0.167],"y":[0.167]},"t":13.186,"s":[70]},{"i":{"x":[0.833],"y":[0.833]},"o":{"x":[0.167],"y":[0.167]},"t":14.385,"s":[0]},{"t":16.7837506836162,"s":[100]}],"ix":11},"r":{"a":0,"k":0,"ix":10},"p":{"a":0,"k":[250.84,248.217,0],"ix":2},"a":{"a":0,"k":[9.753,7.819,0],"ix":1},"s":{"a":0,"k":[2090.073,2090.073,100],"ix":6}},"ao":0,"shapes":[{"ty":"gr","it":[{"ind":0,"ty":"sh","ix":1,"ks":{"a":0,"k":{"i":[[0,-3.973],[3.973,0],[0,3.973],[-3.974,0]],"o":[[0,3.973],[-3.974,0],[0,-3.973],[3.973,0]],"v":[[7.195,0],[0.001,7.194],[-7.195,0],[0.001,-7.194]],"c":true},"ix":2},"nm":"Path 1","mn":"ADBE Vector Shape - Group","hd":false},{"ty":"st","c":{"a":0,"k":[0.066666666667,0.372549019608,0.917647058824,1],"ix":3},"o":{"a":0,"k":100,"ix":4},"w":{"a":0,"k":0.25,"ix":5},"lc":1,"lj":1,"ml":10,"bm":0,"nm":"Stroke 1","mn":"ADBE Vector Graphic - Stroke","hd":false},{"ty":"tr","p":{"a":0,"k":[9.753,7.819],"ix":2},"a":{"a":0,"k":[0,0],"ix":1},"s":{"a":0,"k":[100,100],"ix":3},"r":{"a":0,"k":0,"ix":6},"o":{"a":0,"k":100,"ix":7},"sk":{"a":0,"k":0,"ix":4},"sa":{"a":0,"k":0,"ix":5},"nm":"变换"}],"nm":"Group 3","np":2,"cix":2,"bm":0,"ix":1,"mn":"ADBE Vector Group","hd":false}],"ip":0,"op":2997.00012207031,"st":0,"bm":0},{"ddd":0,"ind":2,"ty":4,"nm":"Group 3","sr":1,"ks":{"o":{"a":1,"k":[{"i":{"x":[0.833],"y":[0.833]},"o":{"x":[0.167],"y":[0.167]},"t":3,"s":[0]},{"i":{"x":[0.833],"y":[0.833]},"o":{"x":[0.167],"y":[0.167]},"t":5.398,"s":[70]},{"i":{"x":[0.833],"y":[0.833]},"o":{"x":[0.167],"y":[0.167]},"t":6.596,"s":[0]},{"i":{"x":[0.833],"y":[0.833]},"o":{"x":[0.167],"y":[0.167]},"t":8.994,"s":[18]},{"i":{"x":[0.833],"y":[0.833]},"o":{"x":[0.167],"y":[0.167]},"t":10.193,"s":[0]},{"i":{"x":[0.833],"y":[0.833]},"o":{"x":[0.167],"y":[0.167]},"t":11.391,"s":[10]},{"i":{"x":[0.833],"y":[0.833]},"o":{"x":[0.167],"y":[0.167]},"t":12.59,"s":[51]},{"i":{"x":[0.833],"y":[0.833]},"o":{"x":[0.167],"y":[0.167]},"t":13.789,"s":[0]},{"i":{"x":[0.833],"y":[0.833]},"o":{"x":[0.167],"y":[0.167]},"t":16.186,"s":[70]},{"i":{"x":[0.833],"y":[0.833]},"o":{"x":[0.167],"y":[0.167]},"t":17.385,"s":[0]},{"t":20.0000008146167,"s":[30]}],"ix":11},"r":{"a":0,"k":0,"ix":10},"p":{"a":0,"k":[250.84,248.217,0],"ix":2},"a":{"a":0,"k":[9.753,7.819,0],"ix":1},"s":{"a":1,"k":[{"i":{"x":[0.13,0.13,0.13],"y":[1,1,1]},"o":{"x":[0.87,0.87,0.87],"y":[0,0,0]},"t":0,"s":[2951.842,2951.842,100]},{"i":{"x":[0.13,0.13,0.13],"y":[1,1,1]},"o":{"x":[0.87,0.87,0.87],"y":[0,0,0]},"t":27,"s":[2239.842,2239.842,100]},{"t":58.0000023623884,"s":[2951.842,2951.842,100]}],"ix":6,"x":"var $bm_rt;\ntry {\n    $bm_rt = loopOut(type = 'cycle', numKeyframes = 0);\n} catch (e) {\n    $bm_rt = value;\n}\n;"}},"ao":0,"shapes":[{"ty":"gr","it":[{"ind":0,"ty":"sh","ix":1,"ks":{"a":0,"k":{"i":[[0,-3.973],[3.973,0],[0,3.973],[-3.974,0]],"o":[[0,3.973],[-3.974,0],[0,-3.973],[3.973,0]],"v":[[7.195,0],[0.001,7.194],[-7.195,0],[0.001,-7.194]],"c":true},"ix":2},"nm":"Path 1","mn":"ADBE Vector Shape - Group","hd":false},{"ty":"st","c":{"a":0,"k":[0.066666666667,0.372549019608,0.917647058824,1],"ix":3},"o":{"a":0,"k":100,"ix":4},"w":{"a":0,"k":0.25,"ix":5},"lc":1,"lj":1,"ml":10,"bm":0,"nm":"Stroke 1","mn":"ADBE Vector Graphic - Stroke","hd":false},{"ty":"tr","p":{"a":0,"k":[9.753,7.819],"ix":2},"a":{"a":0,"k":[0,0],"ix":1},"s":{"a":0,"k":[100,100],"ix":3},"r":{"a":0,"k":0,"ix":6},"o":{"a":0,"k":100,"ix":7},"sk":{"a":0,"k":0,"ix":4},"sa":{"a":0,"k":0,"ix":5},"nm":"变换"}],"nm":"Group 3","np":2,"cix":2,"bm":0,"ix":1,"mn":"ADBE Vector Group","hd":false}],"ip":3.00000012219251,"op":3000.00012219251,"st":3.00000012219251,"bm":0},{"ddd":0,"ind":3,"ty":4,"nm":"Group 1","parent":5,"sr":1,"ks":{"o":{"a":0,"k":100,"ix":11},"r":{"a":0,"k":0,"ix":10},"p":{"a":0,"k":[15.918,7.819,0],"ix":2},"a":{"a":0,"k":[15.918,7.819,0],"ix":1},"s":{"a":0,"k":[100,100,100],"ix":6}},"ao":0,"shapes":[{"ty":"gr","it":[{"ind":0,"ty":"sh","ix":1,"ks":{"a":0,"k":{"i":[[0,0],[0,0]],"o":[[0,0],[0,0]],"v":[[14.899,7.819],[16.937,7.819]],"c":false},"ix":2},"nm":"Path 1","mn":"ADBE Vector Shape - Group","hd":false},{"ty":"st","c":{"a":0,"k":[0.062745098039,0.921568627451,0.890196078431,1],"ix":3},"o":{"a":0,"k":100,"ix":4},"w":{"a":0,"k":1,"ix":5},"lc":1,"lj":1,"ml":10,"bm":0,"nm":"Stroke 1","mn":"ADBE Vector Graphic - Stroke","hd":false},{"ty":"tr","p":{"a":0,"k":[0,0],"ix":2},"a":{"a":0,"k":[0,0],"ix":1},"s":{"a":0,"k":[100,100],"ix":3},"r":{"a":0,"k":0,"ix":6},"o":{"a":0,"k":100,"ix":7},"sk":{"a":0,"k":0,"ix":4},"sa":{"a":0,"k":0,"ix":5},"nm":"变换"}],"nm":"Group 1","np":2,"cix":2,"bm":0,"ix":1,"mn":"ADBE Vector Group","hd":false}],"ip":0,"op":2997.00012207031,"st":0,"bm":0},{"ddd":0,"ind":4,"ty":4,"nm":"Group 2","parent":5,"sr":1,"ks":{"o":{"a":0,"k":100,"ix":11},"r":{"a":0,"k":0,"ix":10},"p":{"a":0,"k":[3.553,7.801,0],"ix":2},"a":{"a":0,"k":[3.553,7.801,0],"ix":1},"s":{"a":0,"k":[100,100,100],"ix":6}},"ao":0,"shapes":[{"ty":"gr","it":[{"ind":0,"ty":"sh","ix":1,"ks":{"a":0,"k":{"i":[[0,0],[0,0]],"o":[[0,0],[0,0]],"v":[[2.5,7.801],[4.607,7.801]],"c":false},"ix":2},"nm":"Path 1","mn":"ADBE Vector Shape - Group","hd":false},{"ty":"st","c":{"a":0,"k":[0.062745098039,0.921568627451,0.890196078431,1],"ix":3},"o":{"a":0,"k":100,"ix":4},"w":{"a":0,"k":1,"ix":5},"lc":1,"lj":1,"ml":10,"bm":0,"nm":"Stroke 1","mn":"ADBE Vector Graphic - Stroke","hd":false},{"ty":"tr","p":{"a":0,"k":[0,0],"ix":2},"a":{"a":0,"k":[0,0],"ix":1},"s":{"a":0,"k":[100,100],"ix":3},"r":{"a":0,"k":0,"ix":6},"o":{"a":0,"k":100,"ix":7},"sk":{"a":0,"k":0,"ix":4},"sa":{"a":0,"k":0,"ix":5},"nm":"变换"}],"nm":"Group 2","np":2,"cix":2,"bm":0,"ix":1,"mn":"ADBE Vector Group","hd":false}],"ip":0,"op":2997.00012207031,"st":0,"bm":0},{"ddd":0,"ind":5,"ty":4,"nm":"Group 4","sr":1,"ks":{"o":{"a":0,"k":100,"ix":11},"r":{"a":1,"k":[{"i":{"x":[0.15],"y":[1]},"o":{"x":[0.85],"y":[0]},"t":0,"s":[374]},{"i":{"x":[0.15],"y":[1]},"o":{"x":[0.85],"y":[0]},"t":49,"s":[0]},{"t":163.000006639126,"s":[0]}],"ix":10,"x":"var $bm_rt;\ntry {\n    $bm_rt = loopOut(type = 'cycle', numKeyframes = 0);\n} catch (e) {\n    $bm_rt = value;\n}\n;"},"p":{"a":0,"k":[250.84,248.217,0],"ix":2},"a":{"a":0,"k":[9.753,7.819,0],"ix":1},"s":{"a":1,"k":[{"i":{"x":[0.09,0.09,0.09],"y":[1,1,1]},"o":{"x":[0.83,0.83,0.83],"y":[0,0,0]},"t":0,"s":[0,0,100]},{"t":22.0000008960784,"s":[2090,2090,100]}],"ix":6}},"ao":0,"shapes":[{"ty":"gr","it":[{"ind":0,"ty":"sh","ix":1,"ks":{"a":0,"k":{"i":[[0,-2.842],[2.842,0],[0,2.842],[-2.842,0]],"o":[[0,2.842],[-2.842,0],[0,-2.842],[2.842,0]],"v":[[5.146,0],[0,5.146],[-5.146,0],[0,-5.146]],"c":true},"ix":2},"nm":"Path 1","mn":"ADBE Vector Shape - Group","hd":false},{"ty":"st","c":{"a":0,"k":[0.062745098039,0.921568627451,0.890196078431,1],"ix":3},"o":{"a":0,"k":100,"ix":4},"w":{"a":0,"k":1,"ix":5},"lc":1,"lj":1,"ml":10,"bm":0,"nm":"Stroke 1","mn":"ADBE Vector Graphic - Stroke","hd":false},{"ty":"tr","p":{"a":0,"k":[9.753,7.819],"ix":2},"a":{"a":0,"k":[0,0],"ix":1},"s":{"a":0,"k":[100,100],"ix":3},"r":{"a":0,"k":0,"ix":6},"o":{"a":0,"k":100,"ix":7},"sk":{"a":0,"k":0,"ix":4},"sa":{"a":0,"k":0,"ix":5},"nm":"变换"}],"nm":"Group 4","np":2,"cix":2,"bm":0,"ix":1,"mn":"ADBE Vector Group","hd":false}],"ip":0,"op":2997.00012207031,"st":0,"bm":0}],"markers":[]}